transcript_tagger_sdk/__init__.py
transcript_tagger_sdk/__main__.py
transcript_tagger_sdk/cli.py
transcript_tagger_sdk/config.py
transcript_tagger_sdk/difficulty_analyzer.py
transcript_tagger_sdk/py.typed
transcript_tagger_sdk/transcript_tagger.py
transcript_tagger-0.1.2.dist-info/LICENSE
transcript_tagger-0.1.2.dist-info/METADATA
transcript_tagger-0.1.2.dist-info/WHEEL
transcript_tagger-0.1.2.dist-info/entry_points.txt
transcript_tagger-0.1.2.dist-info/top_level.txt
transcript_tagger-0.1.2.dist-info/RECORD
