Metadata-Version: 2.1
Name: transcript-tagger
Version: 0.1.2
Summary: A toolkit for tagging and analyzing transcript content using AI
Home-page: https://github.com/yourusername/transcript-tagger
Author: Zixiao Yu
Author-email: your.email@example.com
License: UNKNOWN
Platform: UNKNOWN
Classifier: Programming Language :: Python :: 3
Classifier: Programming Language :: Python :: 3.7
Classifier: Programming Language :: Python :: 3.8
Classifier: Programming Language :: Python :: 3.9
Classifier: License :: OSI Approved :: MIT License
Classifier: Operating System :: OS Independent
Classifier: Intended Audience :: Developers
Classifier: Intended Audience :: Education
Classifier: Topic :: Text Processing :: Linguistic
Classifier: Topic :: Scientific/Engineering :: Artificial Intelligence
Requires-Python: >=3.7
Requires-Dist: openai (>=1.0.0)
Requires-Dist: python-dotenv (>=0.19.0)
Requires-Dist: tenacity (>=8.0.0)
Requires-Dist: textstat (>=0.7.3)
Requires-Dist: wordfreq (>=3.0.0)
